etho/__init__.py
etho/pyetho.py
etho/data/etho.pkl
pyetho-2.0.data/data/data/etho.pkl/etho.pkl
pyetho-2.0.dist-info/METADATA
pyetho-2.0.dist-info/WHEEL
pyetho-2.0.dist-info/top_level.txt
pyetho-2.0.dist-info/RECORD
