Metadata-Version: 2.1
Name: pyetho
Version: 2.0
Summary: Exploration of World Languages
Home-page: https://github.com/i18nsolutionspy/Pyetho
Author: SathishKumar paramasivam Et al.
Author-email: i18nsolutionspy@gmail.com
Project-URL: Bug Tracker, https://github.com/i18nsolutionspy/Pyetho/issues
Classifier: Programming Language :: Python :: 3
Classifier: License :: OSI Approved :: MIT License
Classifier: Operating System :: OS Independent
Requires-Python: >=3.6
